<?xml version="1.0" encoding="utf-8"?>
<LanguageData>

  <GotBredByAnimal.stages.0.label>estuprado(a) por animal</GotBredByAnimal.stages.0.label>
  <GotBredByAnimal.stages.0.description>Meu Deus... eu fui estuprado(a) por um animal. A humilhação...Como vou olhar nos olhos do pessoal de novo? Eu acho que o cheiro ainda está em mim...</GotBredByAnimal.stages.0.description>

  <GotAnalBredByAnimal.stages.0.label>estuprado(a) analmente por animal</GotAnalBredByAnimal.stages.0.label>
  <GotAnalBredByAnimal.stages.0.description>Eu fui estuprado(a)....na bunda...por um animal. Não dá pra ir mais fundo que isso; Eu quero rastejar pra um buraco e morrer. Por favor, não olhem pra mim...</GotAnalBredByAnimal.stages.0.description>

  <MasochistGotBredByAnimal.stages.0.label>estuprado(a) por animal</MasochistGotBredByAnimal.stages.0.label>
  <MasochistGotBredByAnimal.stages.0.description>Um animal me estuprou. Isso me faz sentir tão sujo(a) e errado(a), como uma cadela de cruza...nada mau.</MasochistGotBredByAnimal.stages.0.description>

  <MasochistGotAnalBredByAnimal.stages.0.label>estuprado(a) analmente por animal</MasochistGotAnalBredByAnimal.stages.0.label>
  <MasochistGotAnalBredByAnimal.stages.0.description>Eu fui estuprado(a)....na bunda...por um animal. O jeito que ele me humilhou, montando em mim e destruindo minha bunda sem pensar como se eu fosse um porco que não merece nada melhor...Eu poderia me acostumar com isso.</MasochistGotAnalBredByAnimal.stages.0.description>

  <ZoophileGotBredByAnimal.stages.0.label>cruzou com um animal</ZoophileGotBredByAnimal.stages.0.label>
  <ZoophileGotBredByAnimal.stages.0.description>Um animal fez amor comigo como se eu também fosse um(a)...É muito melhor do que com humanos.</ZoophileGotBredByAnimal.stages.0.description>

  <ZoophileGotAnalBredByAnimal.stages.0.label>cruzou analmente com um animal</ZoophileGotAnalBredByAnimal.stages.0.label>
  <ZoophileGotAnalBredByAnimal.stages.0.description>Um animal me montou analmente e me fez de vadia...O jeito que ele montou em mim e enfiou até me encher com sua semente...Me faz querer me tocar de novo e de novo só de pensar.</ZoophileGotAnalBredByAnimal.stages.0.description>

  <AllowedAnimalToBreed.stages.0.label>cruzou com um animal</AllowedAnimalToBreed.stages.0.label>
  <AllowedAnimalToBreed.stages.0.description>Eu estava tão excitado(a) que eu deixei um animal me montar. Eu sinto vergonha por ter gostado...</AllowedAnimalToBreed.stages.0.description>

  <GotLickedByAnimal.stages.0.label>estuprado(a) por animal</GotLickedByAnimal.stages.0.label>
  <GotLickedByAnimal.stages.0.description>Um animal forçou sua língua dentro de mim.</GotLickedByAnimal.stages.0.description>

  <MasochistGotLickedByAnimal.stages.0.label>estuprado(a) por animal</MasochistGotLickedByAnimal.stages.0.label>
  <MasochistGotLickedByAnimal.stages.0.description>Um animal forçou sua língua dentro de mim. Eu meio que gostei...</MasochistGotLickedByAnimal.stages.0.description>

  <ZoophileGotLickedByAnimal.stages.0.label>destruído(a) por um animal</ZoophileGotLickedByAnimal.stages.0.label>
  <ZoophileGotLickedByAnimal.stages.0.description>Um animal me destruiu...</ZoophileGotLickedByAnimal.stages.0.description>

  <AllowedAnimalToLick.stages.0.label>lambido por um animal</AllowedAnimalToLick.stages.0.label>
  <AllowedAnimalToLick.stages.0.description>Eu deixei um animal me lamber. Eu me sinto envergonhado(a) mas eu meio que gostei...</AllowedAnimalToLick.stages.0.description>


  <!-- Generic type for weirder animal stuff, these normally only happen if the player messes with the defaults too much -->

  <GotGropedByAnimal.stages.0.label>molested by animal</GotGropedByAnimal.stages.0.label>
  <GotGropedByAnimal.stages.0.description>An animal molested me. I feel dirty.</GotGropedByAnimal.stages.0.description>

  <MasochistGotGropedByAnimal.stages.0.label>molested by animal (Masochist)</MasochistGotGropedByAnimal.stages.0.label>
  <MasochistGotGropedByAnimal.stages.0.description>An animal molested me. I kinda liked it...</MasochistGotGropedByAnimal.stages.0.description>

  <ZoophileGotGropedByAnimal.stages.0.label>molested by animal (Zoophile)</ZoophileGotGropedByAnimal.stages.0.label>
  <ZoophileGotGropedByAnimal.stages.0.description>An animal ravished me.</ZoophileGotGropedByAnimal.stages.0.description>

  <AllowedAnimalToGrope.stages.0.label>groped by animal</AllowedAnimalToGrope.stages.0.label>
  <AllowedAnimalToGrope.stages.0.description>I was so horny that I let an animal grope me. I feel ashamed...</AllowedAnimalToGrope.stages.0.description>


</LanguageData>